four_chan_ripper/__init__.py
four_chan_ripper/__main__.py
four_chan_ripper-0.0.3.dist-info/LICENSE.md
four_chan_ripper-0.0.3.dist-info/METADATA
four_chan_ripper-0.0.3.dist-info/WHEEL
four_chan_ripper-0.0.3.dist-info/entry_points.txt
four_chan_ripper-0.0.3.dist-info/top_level.txt
four_chan_ripper-0.0.3.dist-info/RECORD
