Metadata-Version: 2.2
Name: four-chan-ripper
Version: 0.0.3
Summary: Rips the contents of threads on 4chan
Home-page: https://github.com/fastily/four-chan-ripper
Author: Fastily
Author-email: fastily@users.noreply.github.com
Project-URL: Bug Tracker, https://github.com/fastily/four-chan-ripper/issues
Classifier: Natural Language :: English
Classifier: Programming Language :: Python :: 3
Classifier: Programming Language :: Python :: 3.11
Classifier: License :: OSI Approved :: GNU General Public License v3 (GPLv3)
Classifier: Operating System :: OS Independent
Requires-Python: >=3.11
License-File: LICENSE.md
Requires-Dist: beautifulsoup4
Requires-Dist: lxml
Requires-Dist: prompt_toolkit
Requires-Dist: requests
Requires-Dist: rich
Requires-Dist: spawn-user-agent
Dynamic: author
Dynamic: author-email
Dynamic: classifier
Dynamic: description
Dynamic: description-content-type
Dynamic: home-page
Dynamic: project-url
Dynamic: requires-dist
Dynamic: requires-python
Dynamic: summary
